serpwow/__init__.py
serpwow/google_search_results.py
serpwow/test.py
google_search_results_serpwow-1.1.10.dist-info/LICENSE
google_search_results_serpwow-1.1.10.dist-info/METADATA
google_search_results_serpwow-1.1.10.dist-info/WHEEL
google_search_results_serpwow-1.1.10.dist-info/top_level.txt
google_search_results_serpwow-1.1.10.dist-info/RECORD
