Metadata-Version: 2.1
Name: google-search-results-serpwow
Version: 1.1.10
Summary: PIP package to scrape and parse Google, Bing, Yahoo, Yandex, Amazon, Ebay and Naver Search Results using SerpWow. Visit https://serpwow.com to get a free API key.
Home-page: https://github.com/serpwow/google-search-results-python
Author: SerpWow
Author-email: hello@serpwow.com
License: UNKNOWN
Platform: UNKNOWN
Classifier: License :: OSI Approved :: MIT License
Classifier: Programming Language :: Python :: 2.7
Requires-Python: >=2.6, !=3.0.*, !=3.1.*, !=3.2.*
Requires-Dist: requests
